<LexML xsi:schemaLocation="http://www.lexml.gov.br/1.0 ../xsd/lexml-br-rigido.xsd" xmlns:xsi="http://www.w3.org/2001/XMLSchema-instance" xmlns:xlink="http://www.w3.org/1999/xlink" xmlns="http://www.lexml.gov.br/1.0">
      <!--       xsi:schemaLocation="http://www.lexml.gov.br/1.0 http://projeto.lexml.gov.br/esquemas/lexml-br-rigido.xsd" > -->
      <Metadado>
      <Identificacao URN="urn:lex:br:senado.federal:projeto.lei;pls:2017;133@data.evento;leitura;2017-05-03t14.00"/>
    </Metadado>
      <ProjetoNorma>
        <Norma>
          <ParteInicial>
      <Epigrafe id="epigrafe">PROJETO DE LEI DO SENADO Nº 133 DE 2017</Epigrafe>
      <Ementa id="ementa">Altera o <span xlink:href="urn:lex:br:federal:decreto.lei:1967-02-28;288">Decreto-Lei nº 288, de 28 de fevereiro de 1967</span>, que altera as disposições da <span xlink:href="urn:lex:br:federal:lei:1957-06-06;3173">Lei nº 3.173, de 6 de junho de 1957</span>, e regula a Zona Franca de Manaus, para assegurar autonomia administrativa às unidades administrativas descentralizadas da SUFRAMA.</Ementa>
      <Preambulo id="preambulo"><p>O CONGRESSO NACIONAL decreta:</p></Preambulo>
    </ParteInicial>
          <Articulacao><Artigo id="art1">
            
            
            <Rotulo>Art. 1º</Rotulo>
            
            <Caput id="art1_cpt">
            <!--Link: urn:lex:br:federal:decreto.lei:1967-02-28;288!art17-->
            
            
            <p>O <span xlink:href="urn:lex:br:federal:decreto.lei:1967-02-28;288!art17">art. 17 do Decreto-Lei nº 288, de 28 de fevereiro de 1967</span>, passa a vigorar acrescido do seguinte parágrafo único:</p>
            <Alteracao xml:base="urn:lex:br:federal:decreto.lei:1967-02-28;288" id="art1_cpt_alt1">
              <!--Matches: MatchResult(Map(urn:lex:br:federal:decreto.lei:1967-02-28;288 -> MatchByBase(urn:lex:br:federal:decreto.lei:1967-02-28;288,1967,Some((2,28)),Map(art17 -> ExactMatch(URN(1967,Some((2,28)),art17,urn:lex:br:federal:decreto.lei:1967-02-28;288!art17)), art17_cpt -> PrefixMatch(URN(1967,Some((2,28)),art17,urn:lex:br:federal:decreto.lei:1967-02-28;288!art17),art17_cpt), art17_par1 -> PrefixMatch(URN(1967,Some((2,28)),art17,urn:lex:br:federal:decreto.lei:1967-02-28;288!art17),art17_par1)))))-->
              <Artigo xlink:href="art17" id="art1_cpt_alt1_art17" abreAspas="s">
            
            
            <Rotulo>Art. 17.</Rotulo>
            
            <Caput xlink:href="art17_cpt" id="art1_cpt_alt1_art17_cpt" textoOmitido="s">
            
            
            
            
            
          </Caput><Paragrafo xlink:href="art17_par1u" id="art1_cpt_alt1_art17_par1u" fechaAspas="s" notaAlteracao="NR">
            
            
            <Rotulo>Parágrafo único.</Rotulo>
            <p>Às unidades administrativas descentralizadas será assegurada autonomia administrativa, com limites definidos no Regimento Interno da Entidade, para planejar e executar ações visando ao desenvolvimento socioeconômico do Estado em que cada unidade esteja localizada.</p>
            
          </Paragrafo>
          </Artigo>
            </Alteracao>
          </Caput>
          </Artigo><Artigo id="art2">
            
            
            <Rotulo>Art. 2º</Rotulo>
            
            <Caput id="art2_cpt">
            
            
            
            <p>Esta Lei entra em vigor na data de sua publicação.</p>
            
          </Caput>
          </Artigo></Articulacao>
        </Norma>
      </ProjetoNorma>
    </LexML>