<LexML xsi:schemaLocation="http://www.lexml.gov.br/1.0 ../xsd/lexml-br-rigido.xsd" xmlns:xsi="http://www.w3.org/2001/XMLSchema-instance" xmlns:xlink="http://www.w3.org/1999/xlink" xmlns="http://www.lexml.gov.br/1.0">
      <!--       xsi:schemaLocation="http://www.lexml.gov.br/1.0 http://projeto.lexml.gov.br/esquemas/lexml-br-rigido.xsd" > -->
      <Metadado>
      <Identificacao URN="urn:lex:br:senado.federal:projeto.lei;plc:2018;32"/>
    </Metadado>
      <ProjetoNorma>
        <Norma>
          <ParteInicial>
      <Epigrafe id="epigrafe">PROJETO DE LEI DA CÂMARA Nº 32 DE 2018</Epigrafe>
      <Ementa id="ementa">Dispõe sobre atividades da campanha Outubro Rosa.</Ementa>
      <Preambulo id="preambulo"><p>O CONGRESSO NACIONAL decreta:</p><p></p></Preambulo>
    </ParteInicial>
          <Articulacao><Artigo id="art1">
            
            
            <Rotulo>Art. 1º</Rotulo>
            
            <Caput id="art1_cpt">
            
            
            
            <p>Serão realizadas anualmente, no mês de outubro, durante a campanha Outubro Rosa, atividades para conscientização sobre o câncer de mama.</p>
            
          </Caput><Paragrafo id="art1_par1u">
            
            
            <Rotulo>Parágrafo único.</Rotulo>
            <p>A critério dos gestores, devem ser desenvolvidas as seguintes atividades, entre outras:</p>
            <Inciso id="art1_par1u_inc1">
            
            
            <Rotulo>I –</Rotulo>
            <p>iluminação de prédios públicos com luzes de cor rosa;</p>
            
          </Inciso><Inciso id="art1_par1u_inc2">
            
            
            <Rotulo>II –</Rotulo>
            <p>promoção de palestras, eventos e atividades educativas;</p>
            
          </Inciso><Inciso id="art1_par1u_inc3">
            
            
            <Rotulo>III –</Rotulo>
            <p>veiculação de campanhas de mídia e disponibilização à população de informações em banners, em folders e em outros materiais ilustrativos e exemplificativos sobre a prevenção ao câncer, que contemplem a generalidade do tema;</p>
            
          </Inciso><Inciso id="art1_par1u_inc4">
            
            
            <Rotulo>IV –</Rotulo>
            <p>realização de atos lícitos e úteis para a consecução dos objetivos da campanha.</p>
            
          </Inciso>
          </Paragrafo>
          </Artigo><Artigo id="art2">
            
            
            <Rotulo>Art. 2º</Rotulo>
            
            <Caput id="art2_cpt">
            
            
            
            <p>Esta Lei entra em vigor na data de sua publicação.</p>
            
          </Caput>
          </Artigo></Articulacao>
        </Norma>
      </ProjetoNorma>
    </LexML>